inventree_kicad/KiCadLibraryPlugin.py
inventree_kicad/__init__.py
inventree_kicad/admin.py
inventree_kicad/models.py
inventree_kicad/serializers.py
inventree_kicad/version.py
inventree_kicad/viewsets.py
inventree_kicad/migrations/0001_initial.py
inventree_kicad/migrations/0002_auto_20230920_0115.py
inventree_kicad/migrations/0003_selectedcategory_default_reference.py
inventree_kicad/migrations/0004_alter_selectedcategory_options.py
inventree_kicad/migrations/0005_selectedcategory_default_value_parameter_template.py
inventree_kicad/migrations/0006_progressindicator.py
inventree_kicad/migrations/0007_auto_20231212_1720.py
inventree_kicad/migrations/0008_alter_selectedcategory_footprint_parameter_template.py
inventree_kicad/migrations/__init__.py
inventree_kicad/templates/inventree_kicad/kicad_bom_import.html
inventree_kicad_plugin-2.0.3.dist-info/licenses/LICENSE
inventree_kicad_plugin-2.0.3.dist-info/METADATA
inventree_kicad_plugin-2.0.3.dist-info/WHEEL
inventree_kicad_plugin-2.0.3.dist-info/entry_points.txt
inventree_kicad_plugin-2.0.3.dist-info/top_level.txt
inventree_kicad_plugin-2.0.3.dist-info/RECORD
