Metadata-Version: 2.4
Name: inventree-kicad-plugin
Version: 2.0.3
Summary: KiCad HTTP library plugin for InvenTree
Home-page: https://github.com/afkiwers/inventree_kicad
Author: Andre Iwers
Author-email: iwers11@gmail.com
License: MIT
Keywords: inventree kicad pcb schematic inventory
Classifier: Programming Language :: Python :: 3
Classifier: Operating System :: OS Independent
Classifier: Framework :: InvenTree
Requires-Python: >=3.9
License-File: LICENSE
Dynamic: author
Dynamic: author-email
Dynamic: classifier
Dynamic: description
Dynamic: description-content-type
Dynamic: home-page
Dynamic: keywords
Dynamic: license
Dynamic: license-file
Dynamic: requires-python
Dynamic: summary
